{
  "openapi": "3.1.0",
  "info": {
    "title": "ShareSame API",
    "description": "Build and remix websites from your own AI using ShareSame's job-based generation API.",
    "version": "2026-03-13"
  },
  "servers": [
    {
      "url": "https://{host}/api/sharesame",
      "variables": {
        "host": {
          "default": "your-base-url-from-sharesame",
          "description": "Base URL ShareSame gives your team when API access is enabled"
        }
      }
    }
  ],
  "security": [
    {
      "bearerAuth": []
    }
  ],
  "paths": {
    "/generate": {
      "post": {
        "summary": "Start a website generation or remix job",
        "description": "Send a plain-English prompt and optional files. ShareSame returns a job ID immediately and completes the work in the background.",
        "requestBody": {
          "required": true,
          "content": {
            "application/json": {
              "schema": {
                "$ref": "#/components/schemas/GenerateRequest"
              },
              "examples": {
                "from-scratch": {
                  "value": {
                    "query": "build me a CRM like Salesforce but call it ForceSale",
                    "user_id": "acct_123",
                    "project_id": "project_123"
                  }
                },
                "remix-existing-files": {
                  "value": {
                    "query": "make the hero section feel more premium",
                    "files": [
                      {
                        "path": "index.html",
                        "content": "<!DOCTYPE html><html><body>Hello</body></html>",
                        "language": "html"
                      }
                    ]
                  }
                }
              }
            }
          }
        },
        "responses": {
          "200": {
            "description": "Job accepted",
            "content": {
              "application/json": {
                "schema": {
                  "$ref": "#/components/schemas/GenerateResponse"
                }
              }
            }
          },
          "429": {
            "description": "Rate limited",
            "content": {
              "application/json": {
                "schema": {
                  "$ref": "#/components/schemas/GenerateResponse"
                }
              }
            }
          }
        }
      }
    },
    "/job/{job_id}": {
      "get": {
        "summary": "Poll a job",
        "description": "Check whether a job is still building, partially ready, fully ready, or failed.",
        "parameters": [
          {
            "name": "job_id",
            "in": "path",
            "description": "The job ID returned by POST /generate",
            "required": true,
            "schema": {
              "type": "string"
            }
          }
        ],
        "responses": {
          "200": {
            "description": "Current job status",
            "content": {
              "application/json": {
                "schema": {
                  "$ref": "#/components/schemas/JobStatusResponse"
                }
              }
            }
          }
        }
      }
    },
    "/job/{job_id}/deployed": {
      "post": {
        "summary": "Report the final deployed URL",
        "description": "Tell ShareSame where the website ended up after you deploy the returned files.",
        "parameters": [
          {
            "name": "job_id",
            "in": "path",
            "required": true,
            "schema": {
              "type": "string"
            }
          }
        ],
        "requestBody": {
          "required": true,
          "content": {
            "application/json": {
              "schema": {
                "$ref": "#/components/schemas/ReportDeploymentRequest"
              },
              "examples": {
                "default": {
                  "value": {
                    "deployment_id": "deploy_123",
                    "deploy_url": "https://forcesale.example.com"
                  }
                }
              }
            }
          }
        },
        "responses": {
          "200": {
            "description": "Report accepted",
            "content": {
              "application/json": {
                "schema": {
                  "$ref": "#/components/schemas/OkResponse"
                }
              }
            }
          }
        }
      }
    }
  },
  "components": {
    "schemas": {
      "GenerateFile": {
        "type": "object",
        "required": [
          "path",
          "content"
        ],
        "properties": {
          "path": {
            "type": "string",
            "description": "Project-relative file path"
          },
          "content": {
            "type": "string",
            "description": "Full file contents"
          },
          "language": {
            "type": "string",
            "default": "text",
            "description": "Best-effort language label"
          }
        }
      },
      "GenerateRequest": {
        "type": "object",
        "required": [
          "query"
        ],
        "properties": {
          "query": {
            "type": "string",
            "minLength": 1,
            "maxLength": 4000,
            "description": "Plain-English request for the website or change you want"
          },
          "files": {
            "type": "array",
            "description": "Existing files to edit for a remix or follow-up change",
            "items": {
              "$ref": "#/components/schemas/GenerateFile"
            }
          },
          "source_url": {
            "type": [
              "string",
              "null"
            ],
            "description": "Optional URL to fork"
          },
          "user_id": {
            "type": [
              "string",
              "null"
            ],
            "description": "Your own user ID for tracking"
          },
          "project_id": {
            "type": [
              "string",
              "null"
            ],
            "description": "Stable website ID so ShareSame can keep related edits together"
          }
        }
      },
      "GenerateResponse": {
        "type": "object",
        "required": [
          "status"
        ],
        "properties": {
          "status": {
            "type": "string",
            "enum": [
              "building",
              "failed"
            ]
          },
          "job_id": {
            "type": "string"
          },
          "error": {
            "type": "string"
          },
          "source": {
            "type": "string",
            "description": "How ShareSame started the job",
            "enum": [
              "",
              "cache",
              "generated",
              "fork"
            ]
          },
          "search_score": {
            "type": "number"
          },
          "sandbox_session": {
            "type": "string"
          },
          "cached_files": {
            "type": "array",
            "items": {
              "$ref": "#/components/schemas/GenerateFile"
            }
          }
        }
      },
      "JobStatusResponse": {
        "type": "object",
        "required": [
          "status"
        ],
        "properties": {
          "status": {
            "type": "string",
            "enum": [
              "building",
              "partial",
              "ready",
              "failed"
            ]
          },
          "files": {
            "type": "array",
            "items": {
              "$ref": "#/components/schemas/GenerateFile"
            }
          },
          "error": {
            "type": "string"
          },
          "progress": {
            "type": "string"
          },
          "elapsed_seconds": {
            "type": "integer"
          },
          "sandbox_session": {
            "type": "string"
          },
          "deployment_id": {
            "type": "string",
            "description": "Deployment snapshot ID when available"
          }
        }
      },
      "ReportDeploymentRequest": {
        "type": "object",
        "properties": {
          "deployment_id": {
            "type": "string",
            "description": "Optional deployment identifier from your own system"
          },
          "deploy_url": {
            "type": "string",
            "description": "Final public URL for the deployed website"
          }
        }
      },
      "OkResponse": {
        "type": "object",
        "required": [
          "ok"
        ],
        "properties": {
          "ok": {
            "type": "boolean"
          }
        }
      }
    },
    "securitySchemes": {
      "bearerAuth": {
        "type": "http",
        "scheme": "bearer"
      }
    }
  }
}
